MANIFEST.in
README.rst
setup.py
unify.py
unify.egg-info/PKG-INFO
unify.egg-info/SOURCES.txt
unify.egg-info/dependency_links.txt
unify.egg-info/entry_points.txt
unify.egg-info/requires.txt
unify.egg-info/top_level.txt