Metadata-Version: 1.1
Name: unify
Version: 0.3
Summary: Modifies strings to all use the same (single/double) quote where possible.
Home-page: https://github.com/myint/unify
Author: Steven Myint
Author-email: UNKNOWN
License: Expat License
Keywords: strings,formatter,style
Platform: UNKNOWN
Classifier: Intended Audience :: Developers
Classifier: Environment :: Console
Classifier: Programming Language :: Python :: 2.6
Classifier: Programming Language :: Python :: 2.7
Classifier: Programming Language :: Python :: 3
Classifier: License :: OSI Approved :: MIT License
